{
	"#buildup": {
		"add-option": true
	},
	".build-up-follow-on": {
		"delete": true,
		"resize": {
			"resize-peers": true,
			"resize-width": true
		},
		"image": {
			"act-on": ".buildup_inner",
			"show-placeholder":false
		},
		"border": {
			"rounding": true
		},
		"color": true
	},
	"#buildup_1": {
		"resize": {
			"resize-peers": true,
			"resize-width": true
		},
		"border": {
			"rounding": true
		},
		"image": {
			"act-on": ".buildup_inner",
			"show-placeholder":false
		},
		"color": true
	},
	".text_content": {
		"resize": {
			"resize-peers": true,
			"resize-height": true
		},
		"border": {
			"padding": true
		},
		"text": true,
		"font": {
			"size": true
		},
		"inset": true
	}	
}